wildcard_openai/Executor.py
wildcard_openai/OpenAITool.py
wildcard_openai/Prompt.py
wildcard_openai/Retriever.py
wildcard_openai/WildcardClient.py
wildcard_openai/__init__.py
wildcard_openai-0.1.8.dist-info/METADATA
wildcard_openai-0.1.8.dist-info/WHEEL
wildcard_openai-0.1.8.dist-info/RECORD
